aliro_quantum_networking/__init__.py
aliro_quantum_networking/api_client.py
aliro_quantum_networking/configuration.py
aliro_quantum_networking/exceptions.py
aliro_quantum_networking/rest.py
aliro_quantum_networking/api/__init__.py
aliro_quantum_networking/api/authentication_api.py
aliro_quantum_networking/api/submissions_api.py
aliro_quantum_networking/api/user_api.py
aliro_quantum_networking/api/utils_api.py
aliro_quantum_networking/models/__init__.py
aliro_quantum_networking/models/api_key.py
aliro_quantum_networking/models/api_key_response.py
aliro_quantum_networking/models/basic_success.py
aliro_quantum_networking/models/change_password_parameters.py
aliro_quantum_networking/models/classical_channel.py
aliro_quantum_networking/models/credentials_basic.py
aliro_quantum_networking/models/email_info.py
aliro_quantum_networking/models/error_model.py
aliro_quantum_networking/models/login_response.py
aliro_quantum_networking/models/memory_base.py
aliro_quantum_networking/models/memory_input.py
aliro_quantum_networking/models/memory_output.py
aliro_quantum_networking/models/node.py
aliro_quantum_networking/models/node_operation_errors.py
aliro_quantum_networking/models/output.py
aliro_quantum_networking/models/quantum_connection.py
aliro_quantum_networking/models/register_params.py
aliro_quantum_networking/models/register_params_all_of.py
aliro_quantum_networking/models/request.py
aliro_quantum_networking/models/statistics_summary.py
aliro_quantum_networking/models/status.py
aliro_quantum_networking/models/status_title.py
aliro_quantum_networking/models/string_response.py
aliro_quantum_networking/models/submission_aqn_base.py
aliro_quantum_networking/models/submission_aqn_base_global_settings.py
aliro_quantum_networking/models/submission_aqn_input.py
aliro_quantum_networking/models/submission_aqn_input_all_of.py
aliro_quantum_networking/models/submission_aqn_output.py
aliro_quantum_networking/models/submission_aqn_output_all_of.py
aliro_quantum_networking-1.50.0.dist-info/METADATA
aliro_quantum_networking-1.50.0.dist-info/WHEEL
aliro_quantum_networking-1.50.0.dist-info/top_level.txt
aliro_quantum_networking-1.50.0.dist-info/RECORD
